<?xml version="1.0" encoding="UTF-8" standalone="yes"?>
<config>
    <givenCode>name</givenCode>
    <middleNameCode>3name</middleNameCode>
    <familyCode>surname</familyCode>
    <genderCode>sex</genderCode>
    <birthDataCode>datebirth</birthDataCode>
    <placeDataCode>placebirth</placeDataCode>
    <docsMap>
        <entry>
            <key>3.0.0.11</key>
            <value>periodupto</value>
        </entry>
        <entry>
            <key>3.0.0.2</key>
            <value>dateofissue</value>
        </entry>
        <entry>
            <key>3.0.0.10</key>
            <value>periodfrom</value>
        </entry>
        <entry>
            <key>3.0.0.1</key>
            <value>passportnumber</value>
        </entry>
        <entry>
            <key>3.0.0.4</key>
            <value>actbirth</value>
        </entry>
        <entry>
            <key>3.0.0.3</key>
            <value>placeissue</value>
        </entry>
        <entry>
            <key>3.0.0.6</key>
            <value>inn</value>
        </>
        <entry>
            <key>3.0.0.5</key>
            <value>datecertificate</value>
        </entry>
        <entry>
            <key>3.0.0.9</key>
            <value>seriespolicy</value>
        </entry>
        <entry>
            <key>3.0.0.12</key>
            <value>insurancecompany</value>
        </entry>
        <entry>
            <key>3.0.0.7</key>
            <value>snils</value>
        </entry>
        <entry>
            <key>3.0.0.8</key>
            <value>policynumber</value>
        </entry>
    </docsMap>
    <telecomMap>
        <entry>
            <key>MC</key>
            <value>mobilephone</value>
        </entry>
        <entry>
            <key>WP</key>
            <value>workphone</value>
        </entry>
        <entry>
            <key>HP</key>
            <value>homephone</value>
        </entry>
    </telecomMap>
    <addrMap>
        <entry>
            <key>H</key>
            <value>realaddress</value>
        </entry>
        <entry>
            <key>HP</key>
            <value>regaddress</value>
        </entry>
    </addrMap>
</config>
